polywrap_test_cases/__init__.py
polywrap_test_cases/__main__.py
polywrap_test_cases/py.typed
polywrap_test_cases-0.1.2.dist-info/METADATA
polywrap_test_cases-0.1.2.dist-info/WHEEL
polywrap_test_cases-0.1.2.dist-info/RECORD
