Metadata-Version: 2.1
Name: polywrap-test-cases
Version: 0.1.2
Summary: Wrap Test cases for Polywrap
Author: Cesar
Author-email: cesar@polywrap.io
Requires-Python: >=3.10,<4.0
Classifier: Programming Language :: Python :: 3
Classifier: Programming Language :: Python :: 3.10
Classifier: Programming Language :: Python :: 3.11
